LICENSE.txt
MANIFEST.in
README.txt
setup.py
doc/Makefile
doc/README.txt
doc/source/conf.py
doc/source/data_model.rst
doc/source/hdf5.rst
doc/source/index.rst
doc/source/pdb_convention.rst
doc/source/python_api.rst
doc/source/tools.rst
doc/source/xml.rst
lib/mosaic/__init__.py
lib/mosaic/api.py
lib/mosaic/array_model.py
lib/mosaic/h5md.py
lib/mosaic/hdf5.py
lib/mosaic/immutable_model.py
lib/mosaic/molecular_structure.py
lib/mosaic/mutable_model.py
lib/mosaic/utility.py
lib/mosaic/version.py
lib/mosaic/xml_io.py
lib/mosaic_pdb/__init__.py
lib/mosaic_pdb/import_structure.py
lib/mosaic_pdb/mmcif.py
lib/mosaic_pdb/pdb_chem_comp.py
lib/mosaic_pdb/space_groups.py
lib/pyMosaic.egg-info/PKG-INFO
lib/pyMosaic.egg-info/SOURCES.txt
lib/pyMosaic.egg-info/dependency_links.txt
lib/pyMosaic.egg-info/top_level.txt
scripts/mosaic
tests/all_tests.py
tests/array_model_tests.py
tests/basic_tests.py
tests/equivalence_tests.py
tests/h5md_tests.py
tests/hdf5_no_bonds.py
tests/hdf5_tests.py
tests/immutable_model_tests.py
tests/molecular_structure_tests.py
tests/mutable_model_tests.py
tests/pdb_tests.py
tests/xml_tests.py