Metadata-Version: 1.1
Name: pyMosaic
Version: 0.4.0
Summary: MOlecular SimulAtion Interchange Conventions
Home-page: http://github.com/mosaic-data-model/mosaic-python
Author: Konrad Hinsen
Author-email: research@khinsen.fastmail.net
License: BSD
Platform: any
Classifier: Development Status :: 3 - Alpha
Classifier: Intended Audience :: Science/Research
Classifier: License :: OSI Approved :: BSD License
Classifier: Operating System :: OS Independent
Classifier: Programming Language :: Python :: 2.7
Classifier: Programming Language :: Python :: 3.2
Classifier: Programming Language :: Python :: 3.3
Classifier: Topic :: Scientific/Engineering
Requires: numpy (>=1.6)
Requires: h5py (>=2.1)
Requires: ImmutablePy (>=0.1)
Provides: pyMosaic
